README.rst
setup.py
exception_sms/__init__.py
exception_sms/logs_models.py
exception_sms/send_email_module.py
exception_sms/tests.py
exception_sms/to_get_logs.py
exception_sms.egg-info/PKG-INFO
exception_sms.egg-info/SOURCES.txt
exception_sms.egg-info/dependency_links.txt
exception_sms.egg-info/requires.txt
exception_sms.egg-info/top_level.txt