Metadata-Version: 1.1
Name: exception-sms
Version: 0.2.0
Summary: A package to notify developer that program catched a exception
Home-page: https://github.com/Thchoonlophon/exception-sms
Author: Jingxuan
Author-email: jingxuan@lynchow.com
License: MIT License
Platform: UNKNOWN
Classifier: License :: OSI Approved :: MIT License
Classifier: Programming Language :: Python :: 3
Classifier: Programming Language :: Python :: 3.6
Classifier: Programming Language :: Python :: 3.7
Classifier: Programming Language :: Python :: 3.8
